Cinance/__init__.py
Cinance/requests_candle_data.py
Cinance/test_requests_candle_data.py
cinance-0.0.1.dist-info/licenses/LICENSE
cinance-0.0.1.dist-info/METADATA
cinance-0.0.1.dist-info/WHEEL
cinance-0.0.1.dist-info/top_level.txt
cinance-0.0.1.dist-info/RECORD
