Metadata-Version: 2.4
Name: Cinance
Version: 0.0.1
Summary: Library with several features including [get_candle_data_about_minutes, get_candle_data_in_minute, get_candle_data_market, get_candle_data_in_range, get_symbol_list]
Home-page: https://github.com/trgchinhh/LibraryCinance
Author: Nguyen Truong Chinh
Author-email: chinhcuber@gmail.com
Keywords: get_candle_data_about_minutes,get_candle_data_in_minute,get_candle_data_market,get_candle_data_in_range,get_symbol_list
Classifier: Programming Language :: Python :: 3
Classifier: License :: OSI Approved :: MIT License
Classifier: Operating System :: OS Independent
Requires-Python: >=3.6
License-File: LICENSE
Requires-Dist: requests>=2.25.0
Dynamic: author
Dynamic: author-email
Dynamic: classifier
Dynamic: description
Dynamic: description-content-type
Dynamic: home-page
Dynamic: keywords
Dynamic: license-file
Dynamic: requires-dist
Dynamic: requires-python
Dynamic: summary
